[{"paths": ["group1-shard1of1"], "weights": [{"name": "Reshape/shape", "shape": [4], "dtype": "int32"}, {"name": "conv2d/kernel", "shape": [7, 7, 1, 8], "dtype": "float32"}, {"name": "conv2d/bias", "shape": [8], "dtype": "float32"}, {"name": "Reshape_1/shape", "shape": [2], "dtype": "int32"}, {"name": "dense/kernel", "shape": [6272, 64], "dtype": "float32"}, {"name": "dense/bias", "shape": [64], "dtype": "float32"}, {"name": "net_out/kernel", "shape": [64, 10], "dtype": "float32"}, {"name": "net_out/bias", "shape": [10], "dtype": "float32"}]}]